disinfodomains/__init__.py
disinfodomains/disinfodomains.py
disinfo_domains-0.1.0.dist-info/LICENSE
disinfo_domains-0.1.0.dist-info/METADATA
disinfo_domains-0.1.0.dist-info/WHEEL
disinfo_domains-0.1.0.dist-info/top_level.txt
disinfo_domains-0.1.0.dist-info/RECORD
