Metadata-Version: 2.1
Name: disinfo-domains
Version: 0.1.0
Summary: Analyze the reliability of a source using Wikipedia.
Home-page: https://github.com/capjamesg/getsitemap
Author: capjamesg
Author-email: jamesg@jamesg.blog
Classifier: Programming Language :: Python :: 3
Classifier: License :: OSI Approved :: MIT License
Classifier: Operating System :: OS Independent
Requires-Python: >=3.7
License-File: LICENSE
Requires-Dist: transformers
Requires-Dist: validators
Requires-Dist: torch
Requires-Dist: requests
Requires-Dist: pandas
Requires-Dist: mkdocstrings
Provides-Extra: dev
Requires-Dist: flake8 ; extra == 'dev'
Requires-Dist: black ==22.3.0 ; extra == 'dev'
Requires-Dist: isort ; extra == 'dev'
Requires-Dist: twine ; extra == 'dev'
Requires-Dist: pytest ; extra == 'dev'
Requires-Dist: wheel ; extra == 'dev'
